README.md
examples/README.md
examples/advanced_symbol_table.py
examples/arithmetic_operations.py
examples/backend_selection.py
examples/basic_usage.py
examples/comparison_conditionals.py
examples/jupyter_visualization.ipynb
examples/knowledge_graph_reasoning.py
examples/model_persistence.py
examples/provenance_tracking.py
examples/rule_builder_dsl.py
examples/training_workflow.py
pytensorlogic-0.1.0a1.dist-info/METADATA
pytensorlogic-0.1.0a1.dist-info/WHEEL
pytensorlogic.pyi
pytensorlogic/__init__.py
pytensorlogic/__init__.pyi
pytensorlogic/py.typed
pytensorlogic/pytensorlogic.abi3.so
tests/__init__.py
tests/test_execution.py
tests/test_types.py
pytensorlogic-0.1.0a1.dist-info/RECORD
