Metadata-Version: 2.4
Name: pytensorlogic
Version: 0.1.0a1
Classifier: Development Status :: 3 - Alpha
Classifier: Intended Audience :: Science/Research
Classifier: Intended Audience :: Developers
Classifier: License :: OSI Approved :: Apache Software License
Classifier: Programming Language :: Python :: 3
Classifier: Programming Language :: Python :: 3.9
Classifier: Programming Language :: Python :: 3.10
Classifier: Programming Language :: Python :: 3.11
Classifier: Programming Language :: Python :: 3.12
Classifier: Programming Language :: Python :: 3.13
Classifier: Programming Language :: Rust
Classifier: Topic :: Scientific/Engineering :: Artificial Intelligence
Classifier: Topic :: Scientific/Engineering :: Mathematics
Classifier: Topic :: Software Development :: Libraries :: Python Modules
Classifier: Operating System :: OS Independent
Requires-Dist: numpy>=1.20.0
Requires-Dist: pytest>=7.0.0 ; extra == 'dev'
Requires-Dist: pytest-cov>=4.0.0 ; extra == 'dev'
Requires-Dist: mypy>=1.0.0 ; extra == 'dev'
Requires-Dist: black>=23.0.0 ; extra == 'dev'
Requires-Dist: ruff>=0.1.0 ; extra == 'dev'
Requires-Dist: jupyter>=1.0.0 ; extra == 'jupyter'
Requires-Dist: matplotlib>=3.5.0 ; extra == 'jupyter'
Provides-Extra: dev
Provides-Extra: jupyter
Summary: Python bindings for TensorLogic - Logic-as-tensor planning layer
Keywords: logic,tensor,einsum,reasoning,neural-symbolic,ai,machine-learning,knowledge-graph,rdf
Home-Page: https://github.com/cool-japan/tensorlogic
Author-email: KitaSan <info@kitasan.io>
Maintainer-email: KitaSan <info@kitasan.io>
License: Apache-2.0
Requires-Python: >=3.9
Project-URL: Homepage, https://github.com/cool-japan/tensorlogic
Project-URL: Repository, https://github.com/cool-japan/tensorlogic
Project-URL: Documentation, https://github.com/cool-japan/tensorlogic/blob/main/README.md
